{
    "asset": {
        "format": "jpg",
        "id": "1c427541cdef5b32cea9f03420958ffd",
        "name": "00000092.jpg",
        "path": "file:C:/Users/jayap/OneDrive/Desktop/TrainYourOwnYOLO/Data/Source_Images/Training_Images/00000092.jpg",
        "size": {
            "width": 337,
            "height": 275
        },
        "state": 2,
        "type": 1
    },
    "regions": [
        {
            "id": "vcdYzp2Nk",
            "type": "RECTANGLE",
            "tags": [
                "Cow"
            ],
            "boundingBox": {
                "height": 96.64285714285714,
                "width": 110.36946386946397,
                "left": 88.3741258741259,
                "top": 40.07142857142857
            },
            "points": [
                {
                    "x": 88.3741258741259,
                    "y": 40.07142857142857
                },
                {
                    "x": 198.74358974358984,
                    "y": 40.07142857142857
                },
                {
                    "x": 198.74358974358984,
                    "y": 136.71428571428572
                },
                {
                    "x": 88.3741258741259,
                    "y": 136.71428571428572
                }
            ]
        }
    ],
    "version": "2.2.0"
}