{
    "asset": {
        "format": "jpg",
        "id": "ee91c61939373593dc008fb8570d798c",
        "name": "dog.73.jpg",
        "path": "file:C:/Users/jayap/OneDrive/Desktop/TrainYourOwnYOLO/Data/Source_Images/Training_Images/dog.73.jpg",
        "size": {
            "width": 299,
            "height": 227
        },
        "state": 2,
        "type": 1
    },
    "regions": [
        {
            "id": "xMldPRKOM",
            "type": "RECTANGLE",
            "tags": [
                "Dog"
            ],
            "boundingBox": {
                "height": 100.13943945748466,
                "width": 113.89241176778997,
                "left": 167.11732052618925,
                "top": 36.579429561070036
            },
            "points": [
                {
                    "x": 167.11732052618925,
                    "y": 36.579429561070036
                },
                {
                    "x": 281.0097322939792,
                    "y": 36.579429561070036
                },
                {
                    "x": 281.0097322939792,
                    "y": 136.7188690185547
                },
                {
                    "x": 167.11732052618925,
                    "y": 136.7188690185547
                }
            ]
        }
    ],
    "version": "2.2.0"
}